<annotation>
	<folder>Raghu_DS</folder>
	<filename>Akhil_Frame_69.jpg</filename>
	<path>/Users/i859396/Downloads/Raghu_DS/Akhil_Frame_69.jpg</path>
	<source>
		<database>Unknown</database>
	</source>
	<size>
		<width>450</width>
		<height>800</height>
		<depth>3</depth>
	</size>
	<segmented>0</segmented>
	<object>
		<name>helmet</name>
		<pose>Unspecified</pose>
		<truncated>0</truncated>
		<difficult>0</difficult>
		<bndbox>
			<xmin>98</xmin>
			<ymin>95</ymin>
			<xmax>405</xmax>
			<ymax>269</ymax>
		</bndbox>
	</object>
	<object>
		<name>glasses</name>
		<pose>Unspecified</pose>
		<truncated>0</truncated>
		<difficult>0</difficult>
		<bndbox>
			<xmin>142</xmin>
			<ymin>271</ymin>
			<xmax>357</xmax>
			<ymax>339</ymax>
		</bndbox>
	</object>
</annotation>
